rvtools2azmigrate/__init__.py
rvtools2azmigrate/azmigrate_vm.py
rvtools2azmigrate/cli.py
rvtools2azmigrate/config.py
rvtools2azmigrate/convert.py
rvtools2azmigrate/rvtools_vm.py
rvtools2azmigrate-0.2.0.dist-info/AUTHORS.md
rvtools2azmigrate-0.2.0.dist-info/LICENSE
rvtools2azmigrate-0.2.0.dist-info/METADATA
rvtools2azmigrate-0.2.0.dist-info/WHEEL
rvtools2azmigrate-0.2.0.dist-info/entry_points.txt
rvtools2azmigrate-0.2.0.dist-info/top_level.txt
rvtools2azmigrate-0.2.0.dist-info/RECORD
