Metadata-Version: 2.1
Name: rvtools2azmigrate
Version: 0.2.0
Summary: Convert an RVTools export to an Azure Migrate CSV inventory file
Home-page: https://github.com/lrivallain/rvtools2azmigrate
Author: Ludovic Rivallain
License: MIT license
Keywords: rvtools2azmigrate
Classifier: Development Status :: 2 - Pre-Alpha
Classifier: Intended Audience :: Developers
Classifier: License :: OSI Approved :: MIT License
Classifier: Natural Language :: English
Classifier: Programming Language :: Python :: 3.8
Classifier: Programming Language :: Python :: 3.9
Classifier: Programming Language :: Python :: 3.10
Requires-Python: >=3.8
License-File: LICENSE
License-File: AUTHORS.md
Requires-Dist: coloredlogs
Requires-Dist: Click
Requires-Dist: openpyxl
Requires-Dist: rich
Requires-Dist: python-slugify
